collective.classification.tree-1.1.0-py3.11-nspkg.pth
collective/classification/tree/__init__.py
collective/classification/tree/caching.py
collective/classification/tree/configure.zcml
collective/classification/tree/indexers.py
collective/classification/tree/interfaces.py
collective/classification/tree/permissions.zcml
collective/classification/tree/script.py
collective/classification/tree/setuphandlers.py
collective/classification/tree/testing.py
collective/classification/tree/utils.py
collective/classification/tree/vocabularies.py
collective/classification/tree/behaviors/__init__.py
collective/classification/tree/behaviors/classification.py
collective/classification/tree/behaviors/configure.zcml
collective/classification/tree/browser/__init__.py
collective/classification/tree/browser/actions.py
collective/classification/tree/browser/category.py
collective/classification/tree/browser/configure.zcml
collective/classification/tree/browser/container.py
collective/classification/tree/browser/container.py.back
collective/classification/tree/browser/helper.py
collective/classification/tree/browser/overrides/.gitkeep
collective/classification/tree/browser/static/.gitkeep
collective/classification/tree/browser/templates/container.pt
collective/classification/tree/browser/templates/delete_confirmation.pt
collective/classification/tree/browser/tests/__init__.py
collective/classification/tree/browser/tests/test_categories.py
collective/classification/tree/contents/__init__.py
collective/classification/tree/contents/category.py
collective/classification/tree/contents/common.py
collective/classification/tree/contents/configure.zcml
collective/classification/tree/contents/container.py
collective/classification/tree/contents/tests/__init__.py
collective/classification/tree/contents/tests/test_categories.py
collective/classification/tree/form/__init__.py
collective/classification/tree/form/configure.zcml
collective/classification/tree/form/importform.py
collective.classification.tree-1.1.0.dist-info/LICENSE.GPL
collective.classification.tree-1.1.0.dist-info/LICENSE.rst
collective.classification.tree-1.1.0.dist-info/METADATA
collective.classification.tree-1.1.0.dist-info/WHEEL
collective.classification.tree-1.1.0.dist-info/entry_points.txt
collective.classification.tree-1.1.0.dist-info/namespace_packages.txt
collective.classification.tree-1.1.0.dist-info/top_level.txt
collective.classification.tree-1.1.0.dist-info/RECORD
