Metadata-Version: 2.1
Name: collective.classification.tree
Version: 1.1.0
Summary: Addon to manage complex content classification tree
Home-page: https://github.com/imio/collective.classification.tree
Author: Martin Peeters
Author-email: support@imio.be
License: GPL version 2
Project-URL: PyPI, https://pypi.python.org/pypi/collective.classification.tree
Project-URL: Source, https://github.com/imio/collective.classification.tree
Project-URL: Tracker, https://github.com/imio/collective.classification.tree/issues
Keywords: Python Plone CMS
Classifier: Environment :: Web Environment
Classifier: Framework :: Plone
Classifier: Framework :: Plone :: Addon
Classifier: Framework :: Plone :: 4.3
Classifier: Programming Language :: Python
Classifier: Programming Language :: Python :: 2.7
Classifier: Operating System :: OS Independent
Classifier: License :: OSI Approved :: GNU General Public License v2 (GPLv2)
License-File: LICENSE.GPL
License-File: LICENSE.rst
Requires-Dist: setuptools
Requires-Dist: z3c.jbot
Requires-Dist: Products.GenericSetup >=1.8.2
Requires-Dist: plone.api >=1.8.4
Requires-Dist: plone.restapi
Requires-Dist: plone.app.dexterity
Requires-Dist: plone.app.referenceablebehavior
Requires-Dist: plone.app.relationfield
Requires-Dist: plone.app.lockingbehavior
Requires-Dist: plone.schema
Requires-Dist: collective.js.datatables
Requires-Dist: imio.helpers >=1.0.0rc4
Requires-Dist: imio.pyutils
Requires-Dist: Unidecode
Provides-Extra: test
Requires-Dist: plone.app.testing ; extra == 'test'
Requires-Dist: plone.testing ; extra == 'test'
Requires-Dist: plone.app.robotframework[debug] ; extra == 'test'
Requires-Dist: plone.app.contenttypes ; extra == 'test'
